puppys/__init__.py
puppys/decorator/__init__.py
puppys/decorator/light.py
puppys/decorator/new_func.py
puppys/env/__init__.py
puppys/env/env.py
puppys/env/func_env.py
puppys/env/meta.py
puppys/llm/__init__.py
puppys/llm/open_ai.py
puppys/pp/__init__.py
puppys/pp/main.py
puppys/pp/mei.py
puppys/pp/actions/__init__.py
puppys/pp/actions/check.py
puppys/pp/actions/do.py
puppys/pp/actions/do_check.py
puppys/pp/actions/explore.py
puppys/pp/actions/go_to.py
puppys/pp/actions/load_env.py
puppys/pp/actions/rewrite.py
puppys/pp/default_env/__init__.py
puppys/pp/default_env/puppy_vars.py
puppys/pp/default_env/actionflow/__init__.py
puppys/pp/default_env/actionflow/actionflow.py
puppys/pp/default_env/actionflow/parse.py
puppys/pp/default_env/actionflow/puppy_ast_exec.py
puppys/tools/__init__.py
puppys/tools/firecrawl_browser.py
puppys/tools/search.py
puppys/tools/defaultTools/__init__.py
puppys/tools/defaultTools/large_language_model.py
puppys/tools/defaultTools/talk_with_human.py
puppys/utils/custom_partial.py
puppys/utils/local_env.py
puppys/utils/std.py
Puppys-0.0.30.dist-info/METADATA
Puppys-0.0.30.dist-info/WHEEL
Puppys-0.0.30.dist-info/top_level.txt
Puppys-0.0.30.dist-info/RECORD
