Metadata-Version: 2.1
Name: Puppys
Version: 0.0.30
Summary: Framework for Developing an Agentic System
Author: Puppys
License: Copyright (c) 2024 Puppy Agent Tech
Project-URL: Homepage, https://github.com/PuppyAgent/Puppys
Project-URL: Issues, https://github.com/PuppyAgent/Puppys/issues
Keywords: LLM,Agent
Classifier: Development Status :: 3 - Alpha
Classifier: Intended Audience :: Developers
Classifier: Topic :: Software Development :: Libraries :: Python Modules
Classifier: License :: OSI Approved :: MIT License
Classifier: Programming Language :: Python :: 3
Classifier: Operating System :: OS Independent
Requires-Python: >=3.9
Requires-Dist: openai >=1.0.0
Requires-Dist: litellm
Requires-Dist: pandas
Requires-Dist: pdoc
Requires-Dist: python-dotenv
Requires-Dist: requests
Requires-Dist: google-api-python-client
Requires-Dist: loguru
Provides-Extra: dev
Requires-Dist: pytest ; extra == 'dev'
